README.rst
setup.py
tinydb_smartcache/__init__.py
tinydb_smartcache.egg-info/PKG-INFO
tinydb_smartcache.egg-info/SOURCES.txt
tinydb_smartcache.egg-info/dependency_links.txt
tinydb_smartcache.egg-info/requires.txt
tinydb_smartcache.egg-info/top_level.txt
tinydb_smartcache.egg-info/zip-safe